<?xml version="1.0" encoding="UTF-8"?>

<!-- generated on 2024-07-25 08:22:15 by Eclipse SUMO sumo Version 1.20.0
<configuration xmlns:xsi="http://www.w3.org/2001/XMLSchema-instance" xsi:noNamespaceSchemaLocation="http://sumo.dlr.de/xsd/sumoConfiguration.xsd">

    <input>
        <net-file value="sumo_rl/nets/two_intersections/two_intersections.net.xml"/>
        <route-files value="sumo_rl/nets/two_intersections/two_intersections.flow.rou.xml"/>
    </input>

    <output>
        <output-prefix value="TIME"/>
        <tripinfo-output value="sumo_rl/nets/two_intersections/tripinfo.xml"/>
    </output>

    <time>
        <step-length value="0.1"/>
    </time>

    <processing>
        <lateral-resolution value="0.1"/>
    </processing>

    <traci_server>
        <remote-port value="42427"/>
    </traci_server>

    <gui_only>
        <tracker-interval value="0.1"/>
    </gui_only>

</configuration>
-->

<tripinfos xmlns:xsi="http://www.w3.org/2001/XMLSchema-instance" xsi:noNamespaceSchemaLocation="http://sumo.dlr.de/xsd/tripinfo_file.xsd">
    <tripinfo id="flow15.0" depart="3.40" departLane="-E6_0" departPos="5.10" departPosLat="0.00" departSpeed="0.00" departDelay="0.00" arrival="26.80" arrivalLane="-E4_0" arrivalPos="86.40" arrivalPosLat="0.00" arrivalSpeed="13.00" duration="23.40" routeLength="194.90" waitingTime="0.00" waitingCount="0" stopTime="0.00" timeLoss="8.45" rerouteNo="0" devices="tripinfo_flow15.0" vType="type1" speedFactor="0.94" vaporized=""/>
    <tripinfo id="flow29.0" depart="0.40" departLane="E4_0" departPos="5.10" departPosLat="0.00" departSpeed="0.00" departDelay="0.00" arrival="62.00" arrivalLane="-E2_0" arrivalPos="86.40" arrivalPosLat="-0.00" arrivalSpeed="13.32" duration="61.60" routeLength="276.73" waitingTime="18.70" waitingCount="1" stopTime="0.00" timeLoss="41.02" rerouteNo="0" devices="tripinfo_flow29.0" vType="type1" speedFactor="1.06" vaporized=""/>
    <tripinfo id="flow0.0" depart="31.80" departLane="E2_0" departPos="5.10" departPosLat="0.00" departSpeed="0.00" departDelay="0.00" arrival="62.10" arrivalLane="-E1_0" arrivalPos="86.40" arrivalPosLat="0.00" arrivalSpeed="11.86" duration="30.30" routeLength="176.73" waitingTime="0.00" waitingCount="0" stopTime="0.00" timeLoss="14.53" rerouteNo="0" devices="tripinfo_flow0.0" vType="type1" speedFactor="0.86" vaporized=""/>
    <tripinfo id="flow24.0" depart="24.60" departLane="-E5_0" departPos="5.10" departPosLat="0.00" departSpeed="0.00" departDelay="0.00" arrival="69.60" arrivalLane="-E2_0" arrivalPos="86.40" arrivalPosLat="0.00" arrivalSpeed="13.85" duration="45.00" routeLength="294.90" waitingTime="4.20" waitingCount="1" stopTime="0.00" timeLoss="23.76" rerouteNo="0" devices="tripinfo_flow24.0" vType="type1" speedFactor="1.05" vaporized=""/>
    <tripinfo id="flow4.0" depart="24.00" departLane="E2_0" departPos="5.10" departPosLat="0.00" departSpeed="0.00" departDelay="0.00" arrival="73.80" arrivalLane="E6_0" arrivalPos="86.40" arrivalPosLat="0.00" arrivalSpeed="11.51" duration="49.80" routeLength="276.73" waitingTime="4.60" waitingCount="1" stopTime="0.00" timeLoss="24.94" rerouteNo="0" devices="tripinfo_flow4.0" vType="type1" speedFactor="0.83" vaporized=""/>
    <tripinfo id="flow4.1" depart="53.50" departLane="E2_0" departPos="5.10" departPosLat="0.00" departSpeed="0.00" departDelay="1.30" arrival="88.50" arrivalLane="E6_0" arrivalPos="86.40" arrivalPosLat="0.00" arrivalSpeed="12.77" duration="35.00" routeLength="276.73" waitingTime="0.00" waitingCount="0" stopTime="0.00" timeLoss="13.09" rerouteNo="0" devices="tripinfo_flow4.1" vType="type1" speedFactor="0.94" vaporized=""/>
    <tripinfo id="flow7.0" depart="15.60" departLane="E1_0" departPos="5.10" departPosLat="0.00" departSpeed="0.00" departDelay="0.00" arrival="97.70" arrivalLane="-E4_2" arrivalPos="86.40" arrivalPosLat="0.00" arrivalSpeed="12.88" duration="82.10" routeLength="274.04" waitingTime="38.40" waitingCount="1" stopTime="0.00" timeLoss="61.28" rerouteNo="0" devices="tripinfo_flow7.0" vType="type1" speedFactor="1.08" vaporized=""/>
    <tripinfo id="flow1.0" depart="36.30" departLane="E2_0" departPos="5.10" departPosLat="0.00" departSpeed="0.00" departDelay="0.00" arrival="97.90" arrivalLane="E0_2" arrivalPos="86.40" arrivalPosLat="0.00" arrivalSpeed="13.08" duration="61.60" routeLength="192.21" waitingTime="28.40" waitingCount="1" stopTime="0.00" timeLoss="47.26" rerouteNo="0" devices="tripinfo_flow1.0" vType="type1" speedFactor="1.05" vaporized=""/>
    <tripinfo id="flow18.0" depart="7.70" departLane="-E6_0" departPos="5.10" departPosLat="0.00" departSpeed="0.00" departDelay="1.80" arrival="98.00" arrivalLane="-E1_2" arrivalPos="86.40" arrivalPosLat="0.00" arrivalSpeed="13.06" duration="90.30" routeLength="289.52" waitingTime="39.20" waitingCount="2" stopTime="0.00" timeLoss="68.28" rerouteNo="0" devices="tripinfo_flow18.0" vType="type1" speedFactor="1.01" vaporized=""/>
    <tripinfo id="flow18.1" depart="21.10" departLane="-E6_0" departPos="5.10" departPosLat="0.00" departSpeed="0.00" departDelay="0.00" arrival="99.40" arrivalLane="-E1_2" arrivalPos="86.40" arrivalPosLat="0.00" arrivalSpeed="13.14" duration="78.30" routeLength="289.52" waitingTime="26.20" waitingCount="1" stopTime="0.00" timeLoss="56.39" rerouteNo="0" devices="tripinfo_flow18.1" vType="type1" speedFactor="1.03" vaporized=""/>
    <tripinfo id="flow15.1" depart="49.40" departLane="-E6_0" departPos="5.10" departPosLat="0.00" departSpeed="0.00" departDelay="0.00" arrival="106.90" arrivalLane="-E4_0" arrivalPos="86.40" arrivalPosLat="0.00" arrivalSpeed="12.83" duration="57.50" routeLength="194.90" waitingTime="24.20" waitingCount="1" stopTime="0.00" timeLoss="42.36" rerouteNo="0" devices="tripinfo_flow15.1" vType="type1" speedFactor="0.93" vaporized=""/>
    <tripinfo id="flow26.0" depart="26.00" departLane="E4_0" departPos="5.10" departPosLat="0.00" departSpeed="0.00" departDelay="0.00" arrival="107.30" arrivalLane="E6_1" arrivalPos="86.40" arrivalPosLat="0.00" arrivalSpeed="12.28" duration="81.30" routeLength="194.90" waitingTime="47.50" waitingCount="1" stopTime="0.00" timeLoss="65.43" rerouteNo="0" devices="tripinfo_flow26.0" vType="type1" speedFactor="0.89" vaporized=""/>
    <tripinfo id="flow10.0" depart="86.40" departLane="-E0_0" departPos="5.10" departPosLat="0.00" departSpeed="0.00" departDelay="0.00" arrival="112.20" arrivalLane="-E2_0" arrivalPos="86.40" arrivalPosLat="0.00" arrivalSpeed="12.98" duration="25.80" routeLength="176.73" waitingTime="0.00" waitingCount="0" stopTime="0.00" timeLoss="11.58" rerouteNo="0" devices="tripinfo_flow10.0" vType="type1" speedFactor="0.95" vaporized=""/>
    <tripinfo id="flow26.1" depart="91.30" departLane="E4_0" departPos="5.10" departPosLat="0.00" departSpeed="0.00" departDelay="0.00" arrival="114.80" arrivalLane="E6_1" arrivalPos="86.40" arrivalPosLat="0.00" arrivalSpeed="12.89" duration="23.50" routeLength="194.90" waitingTime="0.00" waitingCount="0" stopTime="0.00" timeLoss="8.39" rerouteNo="0" devices="tripinfo_flow26.1" vType="type1" speedFactor="0.93" vaporized=""/>
    <tripinfo id="flow8.0" depart="50.00" departLane="E1_0" departPos="5.10" departPosLat="0.00" departSpeed="0.00" departDelay="0.00" arrival="152.10" arrivalLane="E5_0" arrivalPos="86.40" arrivalPosLat="-0.00" arrivalSpeed="12.20" duration="102.10" routeLength="276.73" waitingTime="52.20" waitingCount="2" stopTime="0.00" timeLoss="78.52" rerouteNo="0" devices="tripinfo_flow8.0" vType="type1" speedFactor="0.88" vaporized=""/>
    <tripinfo id="flow29.1" depart="58.10" departLane="E4_0" departPos="5.10" departPosLat="0.00" departSpeed="0.00" departDelay="0.00" arrival="152.30" arrivalLane="-E2_1" arrivalPos="86.40" arrivalPosLat="0.00" arrivalSpeed="12.96" duration="94.20" routeLength="276.73" waitingTime="43.20" waitingCount="2" stopTime="0.00" timeLoss="72.11" rerouteNo="0" devices="tripinfo_flow29.1" vType="type1" speedFactor="0.94" vaporized=""/>
    <tripinfo id="flow13.0" depart="33.70" departLane="-E0_0" departPos="5.10" departPosLat="0.00" departSpeed="0.00" departDelay="0.00" arrival="155.10" arrivalLane="E5_0" arrivalPos="86.40" arrivalPosLat="-0.00" arrivalSpeed="13.88" duration="121.40" routeLength="292.21" waitingTime="76.10" waitingCount="1" stopTime="0.00" timeLoss="99.95" rerouteNo="0" devices="tripinfo_flow13.0" vType="type1" speedFactor="1.09" vaporized=""/>
    <tripinfo id="flow3.0" depart="74.60" departLane="E2_0" departPos="5.10" departPosLat="0.00" departSpeed="0.00" departDelay="0.00" arrival="159.60" arrivalLane="E5_0" arrivalPos="86.40" arrivalPosLat="0.00" arrivalSpeed="13.53" duration="85.00" routeLength="294.90" waitingTime="44.20" waitingCount="1" stopTime="0.00" timeLoss="63.19" rerouteNo="0" devices="tripinfo_flow3.0" vType="type1" speedFactor="0.97" vaporized=""/>
    <tripinfo id="flow24.1" depart="86.70" departLane="-E5_0" departPos="5.10" departPosLat="0.00" departSpeed="0.00" departDelay="3.70" arrival="160.00" arrivalLane="-E2_1" arrivalPos="86.40" arrivalPosLat="0.00" arrivalSpeed="12.70" duration="73.30" routeLength="294.90" waitingTime="32.30" waitingCount="1" stopTime="0.00" timeLoss="50.13" rerouteNo="0" devices="tripinfo_flow24.1" vType="type1" speedFactor="0.92" vaporized=""/>
    <tripinfo id="flow24.2" depart="97.20" departLane="-E5_0" departPos="5.10" departPosLat="0.00" departSpeed="0.00" departDelay="0.00" arrival="161.40" arrivalLane="-E2_1" arrivalPos="86.40" arrivalPosLat="0.00" arrivalSpeed="13.60" duration="64.20" routeLength="294.90" waitingTime="16.90" waitingCount="1" stopTime="0.00" timeLoss="42.92" rerouteNo="0" devices="tripinfo_flow24.2" vType="type1" speedFactor="1.18" vaporized=""/>
    <tripinfo id="flow22.0" depart="74.80" departLane="-E5_0" departPos="5.10" departPosLat="0.00" departSpeed="0.00" departDelay="0.00" arrival="163.30" arrivalLane="E0_0" arrivalPos="86.40" arrivalPosLat="0.00" arrivalSpeed="12.35" duration="88.50" routeLength="276.73" waitingTime="44.10" waitingCount="1" stopTime="0.00" timeLoss="65.26" rerouteNo="0" devices="tripinfo_flow22.0" vType="type1" speedFactor="0.89" vaporized=""/>
    <tripinfo id="flow4.2" depart="78.90" departLane="E2_0" departPos="5.10" departPosLat="0.00" departSpeed="0.00" departDelay="0.80" arrival="165.60" arrivalLane="E6_0" arrivalPos="86.40" arrivalPosLat="0.00" arrivalSpeed="11.46" duration="86.70" routeLength="276.73" waitingTime="35.70" waitingCount="2" stopTime="0.00" timeLoss="61.68" rerouteNo="0" devices="tripinfo_flow4.2" vType="type1" speedFactor="0.83" vaporized=""/>
    <tripinfo id="flow22.1" depart="82.30" departLane="-E5_0" departPos="5.10" departPosLat="0.00" departSpeed="0.00" departDelay="0.00" arrival="166.00" arrivalLane="E0_0" arrivalPos="86.40" arrivalPosLat="0.00" arrivalSpeed="12.10" duration="83.70" routeLength="276.73" waitingTime="31.70" waitingCount="1" stopTime="0.00" timeLoss="59.95" rerouteNo="0" devices="tripinfo_flow22.1" vType="type1" speedFactor="0.87" vaporized=""/>
    <tripinfo id="flow3.1" depart="88.10" departLane="E2_0" departPos="5.10" departPosLat="0.00" departSpeed="0.00" departDelay="0.00" arrival="171.50" arrivalLane="E5_0" arrivalPos="86.40" arrivalPosLat="-0.00" arrivalSpeed="13.74" duration="83.40" routeLength="294.90" waitingTime="30.70" waitingCount="1" stopTime="0.00" timeLoss="62.15" rerouteNo="0" devices="tripinfo_flow3.1" vType="type1" speedFactor="1.13" vaporized=""/>
    <tripinfo id="flow2.1" depart="60.60" departLane="E2_0" departPos="5.10" departPosLat="0.00" departSpeed="0.00" departDelay="0.00" arrival="187.60" arrivalLane="-E4_2" arrivalPos="86.40" arrivalPosLat="0.00" arrivalSpeed="13.01" duration="127.00" routeLength="292.21" waitingTime="81.80" waitingCount="1" stopTime="0.00" timeLoss="105.69" rerouteNo="0" devices="tripinfo_flow2.1" vType="type1" speedFactor="1.16" vaporized=""/>
    <tripinfo id="flow23.0" depart="29.20" departLane="-E5_0" departPos="5.10" departPosLat="0.00" departSpeed="0.00" departDelay="0.00" arrival="187.80" arrivalLane="-E1_2" arrivalPos="86.40" arrivalPosLat="0.00" arrivalSpeed="12.89" duration="158.60" routeLength="292.21" waitingTime="97.70" waitingCount="2" stopTime="0.00" timeLoss="135.49" rerouteNo="0" devices="tripinfo_flow23.0" vType="type1" speedFactor="0.94" vaporized=""/>
    <tripinfo id="flow18.2" depart="35.70" departLane="-E6_0" departPos="5.10" departPosLat="0.00" departSpeed="0.00" departDelay="0.00" arrival="189.30" arrivalLane="-E1_2" arrivalPos="86.40" arrivalPosLat="0.00" arrivalSpeed="13.35" duration="153.60" routeLength="289.52" waitingTime="95.90" waitingCount="2" stopTime="0.00" timeLoss="131.60" rerouteNo="0" devices="tripinfo_flow18.2" vType="type1" speedFactor="1.03" vaporized=""/>
    <tripinfo id="flow10.1" depart="138.50" departLane="-E0_0" departPos="5.10" departPosLat="0.00" departSpeed="0.00" departDelay="0.00" arrival="196.00" arrivalLane="-E2_0" arrivalPos="86.40" arrivalPosLat="0.00" arrivalSpeed="12.01" duration="57.50" routeLength="176.73" waitingTime="25.50" waitingCount="1" stopTime="0.00" timeLoss="44.17" rerouteNo="0" devices="tripinfo_flow10.1" vType="type1" speedFactor="1.18" vaporized=""/>
    <tripinfo id="flow11.0" depart="162.80" departLane="-E0_0" departPos="5.10" departPosLat="0.00" departSpeed="0.00" departDelay="0.00" arrival="197.40" arrivalLane="-E1_1" arrivalPos="86.40" arrivalPosLat="0.00" arrivalSpeed="12.97" duration="34.60" routeLength="194.90" waitingTime="0.80" waitingCount="1" stopTime="0.00" timeLoss="20.56" rerouteNo="0" devices="tripinfo_flow11.0" vType="type1" speedFactor="1.04" vaporized=""/>
    <tripinfo id="flow6.0" depart="198.80" departLane="E1_0" departPos="5.10" departPosLat="0.00" departSpeed="0.00" departDelay="0.00" arrival="233.10" arrivalLane="-E2_2" arrivalPos="86.40" arrivalPosLat="0.00" arrivalSpeed="12.75" duration="34.30" routeLength="192.21" waitingTime="0.70" waitingCount="1" stopTime="0.00" timeLoss="20.20" rerouteNo="0" devices="tripinfo_flow6.0" vType="type1" speedFactor="1.17" vaporized=""/>
    <tripinfo id="flow21.0" depart="176.60" departLane="-E5_0" departPos="5.10" departPosLat="0.00" departSpeed="0.00" departDelay="1.40" arrival="240.50" arrivalLane="-E4_0" arrivalPos="86.40" arrivalPosLat="0.00" arrivalSpeed="12.06" duration="63.90" routeLength="176.73" waitingTime="32.10" waitingCount="1" stopTime="0.00" timeLoss="50.35" rerouteNo="0" devices="tripinfo_flow21.0" vType="type1" speedFactor="1.00" vaporized=""/>
    <tripinfo id="flow0.1" depart="161.30" departLane="E2_0" departPos="5.10" departPosLat="0.00" departSpeed="0.00" departDelay="0.00" arrival="240.60" arrivalLane="-E1_0" arrivalPos="86.40" arrivalPosLat="0.00" arrivalSpeed="11.91" duration="79.30" routeLength="176.73" waitingTime="47.40" waitingCount="1" stopTime="0.00" timeLoss="65.89" rerouteNo="0" devices="tripinfo_flow0.1" vType="type1" speedFactor="1.04" vaporized=""/>
    <tripinfo id="flow9.0" depart="132.60" departLane="E1_0" departPos="5.10" departPosLat="0.00" departSpeed="0.00" departDelay="0.00" arrival="242.10" arrivalLane="E6_0" arrivalPos="86.40" arrivalPosLat="0.00" arrivalSpeed="12.48" duration="109.50" routeLength="258.56" waitingTime="54.20" waitingCount="2" stopTime="0.00" timeLoss="88.90" rerouteNo="0" devices="tripinfo_flow9.0" vType="type1" speedFactor="0.97" vaporized=""/>
    <tripinfo id="flow8.1" depart="121.10" departLane="E1_0" departPos="5.10" departPosLat="0.00" departSpeed="0.00" departDelay="0.00" arrival="242.50" arrivalLane="E5_0" arrivalPos="86.40" arrivalPosLat="0.00" arrivalSpeed="13.13" duration="121.40" routeLength="276.73" waitingTime="71.40" waitingCount="2" stopTime="0.00" timeLoss="100.92" rerouteNo="0" devices="tripinfo_flow8.1" vType="type1" speedFactor="1.17" vaporized=""/>
    <tripinfo id="flow9.1" depart="153.70" departLane="E1_0" departPos="5.10" departPosLat="0.00" departSpeed="0.00" departDelay="0.00" arrival="243.50" arrivalLane="E6_0" arrivalPos="86.40" arrivalPosLat="0.00" arrivalSpeed="13.03" duration="89.80" routeLength="258.56" waitingTime="33.10" waitingCount="2" stopTime="0.00" timeLoss="69.86" rerouteNo="0" devices="tripinfo_flow9.1" vType="type1" speedFactor="1.09" vaporized=""/>
    <tripinfo id="flow19.0" depart="142.60" departLane="-E6_0" departPos="5.10" departPosLat="0.00" departSpeed="0.00" departDelay="2.70" arrival="244.30" arrivalLane="-E2_1" arrivalPos="86.40" arrivalPosLat="0.00" arrivalSpeed="12.50" duration="101.70" routeLength="292.21" waitingTime="53.70" waitingCount="1" stopTime="0.00" timeLoss="77.69" rerouteNo="0" devices="tripinfo_flow19.0" vType="type1" speedFactor="0.90" vaporized=""/>
    <tripinfo id="flow9.2" depart="186.80" departLane="E1_0" departPos="5.10" departPosLat="0.00" departSpeed="0.00" departDelay="0.00" arrival="246.00" arrivalLane="E6_0" arrivalPos="86.40" arrivalPosLat="0.00" arrivalSpeed="11.80" duration="59.20" routeLength="258.56" waitingTime="8.80" waitingCount="1" stopTime="0.00" timeLoss="35.51" rerouteNo="0" devices="tripinfo_flow9.2" vType="type1" speedFactor="0.85" vaporized=""/>
    <tripinfo id="flow14.0" depart="124.70" departLane="-E0_0" departPos="5.10" departPosLat="0.00" departSpeed="0.00" departDelay="0.00" arrival="248.40" arrivalLane="E6_0" arrivalPos="86.40" arrivalPosLat="-0.00" arrivalSpeed="13.03" duration="123.70" routeLength="274.04" waitingTime="75.00" waitingCount="1" stopTime="0.00" timeLoss="102.50" rerouteNo="0" devices="tripinfo_flow14.0" vType="type1" speedFactor="0.99" vaporized=""/>
    <tripinfo id="flow21.1" depart="224.20" departLane="-E5_0" departPos="5.10" departPosLat="0.00" departSpeed="0.00" departDelay="0.00" arrival="249.50" arrivalLane="-E4_0" arrivalPos="86.40" arrivalPosLat="0.00" arrivalSpeed="13.13" duration="25.30" routeLength="176.73" waitingTime="0.00" waitingCount="0" stopTime="0.00" timeLoss="11.85" rerouteNo="0" devices="tripinfo_flow21.1" vType="type1" speedFactor="1.02" vaporized=""/>
    <tripinfo id="flow22.2" depart="195.30" departLane="-E5_0" departPos="5.10" departPosLat="0.00" departSpeed="0.00" departDelay="0.00" arrival="254.90" arrivalLane="E0_0" arrivalPos="86.40" arrivalPosLat="0.00" arrivalSpeed="11.87" duration="59.60" routeLength="276.73" waitingTime="8.70" waitingCount="1" stopTime="0.00" timeLoss="35.45" rerouteNo="0" devices="tripinfo_flow22.2" vType="type1" speedFactor="0.85" vaporized=""/>
    <tripinfo id="flow4.3" depart="223.40" departLane="E2_0" departPos="5.10" departPosLat="0.00" departSpeed="0.00" departDelay="0.00" arrival="256.80" arrivalLane="E6_0" arrivalPos="86.40" arrivalPosLat="0.00" arrivalSpeed="13.53" duration="33.40" routeLength="276.73" waitingTime="0.00" waitingCount="0" stopTime="0.00" timeLoss="12.89" rerouteNo="0" devices="tripinfo_flow4.3" vType="type1" speedFactor="1.14" vaporized=""/>
    <tripinfo id="flow2.0" depart="49.20" departLane="E2_0" departPos="5.10" departPosLat="0.00" departSpeed="0.00" departDelay="0.00" arrival="277.80" arrivalLane="-E4_2" arrivalPos="86.40" arrivalPosLat="0.00" arrivalSpeed="12.93" duration="228.60" routeLength="292.21" waitingTime="183.00" waitingCount="3" stopTime="0.00" timeLoss="206.77" rerouteNo="0" devices="tripinfo_flow2.0" vType="type1" speedFactor="0.99" vaporized=""/>
    <tripinfo id="flow20.0" depart="180.90" departLane="-E5_0" departPos="5.10" departPosLat="0.00" departSpeed="0.00" departDelay="5.10" arrival="277.80" arrivalLane="E6_2" arrivalPos="86.40" arrivalPosLat="0.00" arrivalSpeed="12.49" duration="96.90" routeLength="192.21" waitingTime="63.70" waitingCount="1" stopTime="0.00" timeLoss="80.87" rerouteNo="0" devices="tripinfo_flow20.0" vType="type1" speedFactor="0.90" vaporized=""/>
    <tripinfo id="flow18.3" depart="45.30" departLane="-E6_0" departPos="5.10" departPosLat="0.00" departSpeed="0.00" departDelay="0.00" arrival="278.20" arrivalLane="-E1_2" arrivalPos="86.40" arrivalPosLat="0.00" arrivalSpeed="12.92" duration="232.90" routeLength="289.52" waitingTime="161.80" waitingCount="3" stopTime="0.00" timeLoss="211.37" rerouteNo="0" devices="tripinfo_flow18.3" vType="type1" speedFactor="1.12" vaporized=""/>
    <tripinfo id="flow7.1" depart="61.10" departLane="E1_0" departPos="5.10" departPosLat="0.00" departSpeed="0.00" departDelay="0.00" arrival="279.30" arrivalLane="-E4_2" arrivalPos="86.40" arrivalPosLat="0.00" arrivalSpeed="13.36" duration="218.20" routeLength="274.04" waitingTime="153.30" waitingCount="4" stopTime="0.00" timeLoss="197.15" rerouteNo="0" devices="tripinfo_flow7.1" vType="type1" speedFactor="1.02" vaporized=""/>
    <tripinfo id="flow23.1" depart="114.90" departLane="-E5_0" departPos="5.10" departPosLat="0.00" departSpeed="0.00" departDelay="0.00" arrival="279.40" arrivalLane="-E1_2" arrivalPos="86.40" arrivalPosLat="0.00" arrivalSpeed="13.31" duration="164.50" routeLength="292.21" waitingTime="96.20" waitingCount="4" stopTime="0.00" timeLoss="143.18" rerouteNo="0" devices="tripinfo_flow23.1" vType="type1" speedFactor="1.15" vaporized=""/>
    <tripinfo id="flow11.1" depart="237.50" departLane="-E0_0" departPos="5.10" departPosLat="0.00" departSpeed="0.00" departDelay="0.00" arrival="287.10" arrivalLane="-E1_0" arrivalPos="86.40" arrivalPosLat="0.00" arrivalSpeed="13.10" duration="49.60" routeLength="194.90" waitingTime="16.40" waitingCount="1" stopTime="0.00" timeLoss="35.57" rerouteNo="0" devices="tripinfo_flow11.1" vType="type1" speedFactor="1.12" vaporized=""/>
    <tripinfo id="flow11.2" depart="241.80" departLane="-E0_0" departPos="5.10" departPosLat="0.00" departSpeed="0.00" departDelay="2.70" arrival="287.10" arrivalLane="-E1_1" arrivalPos="86.40" arrivalPosLat="0.00" arrivalSpeed="13.08" duration="45.30" routeLength="194.90" waitingTime="10.90" waitingCount="1" stopTime="0.00" timeLoss="31.25" rerouteNo="0" devices="tripinfo_flow11.2" vType="type1" speedFactor="1.02" vaporized=""/>
    <tripinfo id="flow5.0" depart="202.60" departLane="E1_0" departPos="5.10" departPosLat="0.00" departSpeed="0.00" departDelay="0.20" arrival="287.30" arrivalLane="E0_0" arrivalPos="86.40" arrivalPosLat="-0.00" arrivalSpeed="13.01" duration="84.70" routeLength="194.90" waitingTime="51.00" waitingCount="1" stopTime="0.00" timeLoss="70.59" rerouteNo="0" devices="tripinfo_flow5.0" vType="type1" speedFactor="1.02" vaporized=""/>
    <tripinfo id="flow10.2" depart="261.30" departLane="-E0_0" departPos="5.10" departPosLat="0.00" departSpeed="0.00" departDelay="0.00" arrival="287.60" arrivalLane="-E2_0" arrivalPos="86.40" arrivalPosLat="0.00" arrivalSpeed="13.16" duration="26.30" routeLength="176.73" waitingTime="0.00" waitingCount="0" stopTime="0.00" timeLoss="12.90" rerouteNo="0" devices="tripinfo_flow10.2" vType="type1" speedFactor="1.04" vaporized=""/>
    <tripinfo id="flow26.2" depart="265.00" departLane="E4_0" departPos="5.10" departPosLat="0.00" departSpeed="0.00" departDelay="0.00" arrival="288.30" arrivalLane="E6_0" arrivalPos="86.40" arrivalPosLat="0.00" arrivalSpeed="13.49" duration="23.30" routeLength="194.90" waitingTime="0.00" waitingCount="0" stopTime="0.00" timeLoss="8.82" rerouteNo="0" devices="tripinfo_flow26.2" vType="type1" speedFactor="0.97" vaporized=""/>
    <tripinfo id="flow25.0" depart="224.70" departLane="E4_0" departPos="5.10" departPosLat="0.00" departSpeed="0.00" departDelay="0.00" arrival="323.00" arrivalLane="E5_2" arrivalPos="86.40" arrivalPosLat="0.00" arrivalSpeed="12.95" duration="98.30" routeLength="192.21" waitingTime="65.30" waitingCount="1" stopTime="0.00" timeLoss="84.01" rerouteNo="0" devices="tripinfo_flow25.0" vType="type1" speedFactor="1.08" vaporized=""/>
    <tripinfo id="flow19.1" depart="146.30" departLane="-E6_0" departPos="5.10" departPosLat="0.00" departSpeed="0.00" departDelay="1.30" arrival="330.50" arrivalLane="-E2_1" arrivalPos="86.40" arrivalPosLat="0.00" arrivalSpeed="13.84" duration="184.20" routeLength="292.21" waitingTime="131.50" waitingCount="2" stopTime="0.00" timeLoss="162.63" rerouteNo="0" devices="tripinfo_flow19.1" vType="type1" speedFactor="1.03" vaporized=""/>
    <tripinfo id="flow9.3" depart="224.30" departLane="E1_0" departPos="5.10" departPosLat="0.00" departSpeed="0.00" departDelay="0.00" arrival="330.70" arrivalLane="E6_0" arrivalPos="86.40" arrivalPosLat="0.00" arrivalSpeed="12.10" duration="106.40" routeLength="258.56" waitingTime="52.20" waitingCount="2" stopTime="0.00" timeLoss="85.63" rerouteNo="0" devices="tripinfo_flow9.3" vType="type1" speedFactor="0.97" vaporized=""/>
    <tripinfo id="flow27.0" depart="286.90" departLane="E4_0" departPos="5.10" departPosLat="0.00" departSpeed="0.00" departDelay="0.00" arrival="330.80" arrivalLane="E0_0" arrivalPos="86.40" arrivalPosLat="0.00" arrivalSpeed="12.13" duration="43.90" routeLength="258.56" waitingTime="1.80" waitingCount="1" stopTime="0.00" timeLoss="22.83" rerouteNo="0" devices="tripinfo_flow27.0" vType="type1" speedFactor="0.96" vaporized=""/>
    <tripinfo id="flow21.2" depart="286.80" departLane="-E5_0" departPos="5.10" departPosLat="0.00" departSpeed="0.00" departDelay="0.00" arrival="332.00" arrivalLane="-E4_0" arrivalPos="86.40" arrivalPosLat="0.00" arrivalSpeed="12.30" duration="45.20" routeLength="176.73" waitingTime="7.10" waitingCount="1" stopTime="0.00" timeLoss="31.80" rerouteNo="0" devices="tripinfo_flow21.2" vType="type1" speedFactor="1.06" vaporized=""/>
    <tripinfo id="flow0.2" depart="296.80" departLane="E2_0" departPos="5.10" departPosLat="0.00" departSpeed="0.00" departDelay="2.30" arrival="333.50" arrivalLane="-E1_0" arrivalPos="86.40" arrivalPosLat="-0.00" arrivalSpeed="12.90" duration="36.70" routeLength="176.73" waitingTime="0.00" waitingCount="0" stopTime="0.00" timeLoss="23.29" rerouteNo="0" devices="tripinfo_flow0.2" vType="type1" speedFactor="1.03" vaporized=""/>
    <tripinfo id="flow21.3" depart="308.70" departLane="-E5_0" departPos="5.10" departPosLat="0.00" departSpeed="0.00" departDelay="0.00" arrival="335.40" arrivalLane="-E4_0" arrivalPos="86.40" arrivalPosLat="0.00" arrivalSpeed="13.29" duration="26.70" routeLength="176.73" waitingTime="0.00" waitingCount="0" stopTime="0.00" timeLoss="13.25" rerouteNo="0" devices="tripinfo_flow21.3" vType="type1" speedFactor="1.09" vaporized=""/>
    <tripinfo id="flow24.3" depart="261.40" departLane="-E5_0" departPos="5.10" departPosLat="0.00" departSpeed="0.00" departDelay="0.00" arrival="339.30" arrivalLane="-E2_0" arrivalPos="86.40" arrivalPosLat="0.00" arrivalSpeed="13.89" duration="77.90" routeLength="294.90" waitingTime="37.30" waitingCount="1" stopTime="0.00" timeLoss="56.64" rerouteNo="0" devices="tripinfo_flow24.3" vType="type1" speedFactor="1.02" vaporized=""/>
    <tripinfo id="flow24.4" depart="277.70" departLane="-E5_0" departPos="5.10" departPosLat="0.00" departSpeed="0.00" departDelay="0.00" arrival="339.80" arrivalLane="-E2_1" arrivalPos="86.40" arrivalPosLat="0.00" arrivalSpeed="13.04" duration="62.10" routeLength="294.90" waitingTime="21.10" waitingCount="1" stopTime="0.00" timeLoss="39.48" rerouteNo="0" devices="tripinfo_flow24.4" vType="type1" speedFactor="0.94" vaporized=""/>
    <tripinfo id="flow13.1" depart="217.40" departLane="-E0_0" departPos="5.10" departPosLat="0.00" departSpeed="0.00" departDelay="0.00" arrival="340.10" arrivalLane="E5_0" arrivalPos="86.40" arrivalPosLat="-0.00" arrivalSpeed="13.78" duration="122.70" routeLength="292.21" waitingTime="69.90" waitingCount="1" stopTime="0.00" timeLoss="100.93" rerouteNo="0" devices="tripinfo_flow13.1" vType="type1" speedFactor="1.00" vaporized=""/>
    <tripinfo id="flow30.0" depart="250.80" departLane="E2_0" departPos="5.10" departPosLat="0.00" departSpeed="0.00" departDelay="0.00" arrival="342.20" arrivalLane="E5_0" arrivalPos="86.40" arrivalPosLat="-0.00" arrivalSpeed="12.21" duration="91.40" routeLength="294.90" waitingTime="48.00" waitingCount="1" stopTime="0.00" timeLoss="67.30" rerouteNo="0" devices="tripinfo_flow30.0" vType="type2" speedFactor="0.88" vaporized=""/>
    <tripinfo id="flow22.3" depart="296.60" departLane="-E5_0" departPos="5.10" departPosLat="0.00" departSpeed="0.00" departDelay="0.00" arrival="344.90" arrivalLane="E0_0" arrivalPos="86.40" arrivalPosLat="0.00" arrivalSpeed="13.02" duration="48.30" routeLength="276.73" waitingTime="0.00" waitingCount="0" stopTime="0.00" timeLoss="27.67" rerouteNo="0" devices="tripinfo_flow22.3" vType="type1" speedFactor="1.01" vaporized=""/>
    <tripinfo id="flow4.4" depart="255.20" departLane="E2_0" departPos="5.10" departPosLat="0.00" departSpeed="0.00" departDelay="0.00" arrival="345.60" arrivalLane="E6_0" arrivalPos="86.40" arrivalPosLat="0.00" arrivalSpeed="12.56" duration="90.40" routeLength="276.73" waitingTime="39.00" waitingCount="1" stopTime="0.00" timeLoss="67.54" rerouteNo="0" devices="tripinfo_flow4.4" vType="type1" speedFactor="0.91" vaporized=""/>
    <tripinfo id="flow22.4" depart="317.90" departLane="-E5_0" departPos="5.10" departPosLat="0.00" departSpeed="0.00" departDelay="0.00" arrival="352.10" arrivalLane="E0_0" arrivalPos="86.40" arrivalPosLat="0.00" arrivalSpeed="13.25" duration="34.20" routeLength="276.73" waitingTime="0.00" waitingCount="0" stopTime="0.00" timeLoss="13.55" rerouteNo="0" devices="tripinfo_flow22.4" vType="type1" speedFactor="1.02" vaporized=""/>
    <tripinfo id="flow30.1" depart="293.50" departLane="E2_0" departPos="5.10" departPosLat="0.00" departSpeed="0.00" departDelay="0.00" arrival="352.60" arrivalLane="E5_0" arrivalPos="86.40" arrivalPosLat="-0.00" arrivalSpeed="13.64" duration="59.10" routeLength="294.90" waitingTime="5.40" waitingCount="1" stopTime="0.00" timeLoss="37.52" rerouteNo="0" devices="tripinfo_flow30.1" vType="type2" speedFactor="0.98" vaporized=""/>
    <tripinfo id="flow0.3" depart="330.10" departLane="E2_0" departPos="5.10" departPosLat="0.00" departSpeed="0.00" departDelay="0.00" arrival="355.20" arrivalLane="-E1_0" arrivalPos="86.40" arrivalPosLat="0.00" arrivalSpeed="13.16" duration="25.10" routeLength="176.73" waitingTime="0.00" waitingCount="0" stopTime="0.00" timeLoss="11.69" rerouteNo="0" devices="tripinfo_flow0.3" vType="type1" speedFactor="1.04" vaporized=""/>
    <tripinfo id="flow4.5" depart="325.00" departLane="E2_0" departPos="5.10" departPosLat="0.00" departSpeed="0.00" departDelay="0.00" arrival="359.60" arrivalLane="E6_0" arrivalPos="86.40" arrivalPosLat="0.00" arrivalSpeed="12.99" duration="34.60" routeLength="276.73" waitingTime="0.00" waitingCount="0" stopTime="0.00" timeLoss="13.37" rerouteNo="0" devices="tripinfo_flow4.5" vType="type1" speedFactor="0.98" vaporized=""/>
    <tripinfo id="flow28.0" depart="119.60" departLane="E4_0" departPos="5.10" departPosLat="0.00" departSpeed="0.00" departDelay="0.00" arrival="368.00" arrivalLane="-E1_2" arrivalPos="86.40" arrivalPosLat="0.00" arrivalSpeed="13.05" duration="248.40" routeLength="274.04" waitingTime="187.00" waitingCount="3" stopTime="0.00" timeLoss="227.31" rerouteNo="0" devices="tripinfo_flow28.0" vType="type1" speedFactor="1.01" vaporized=""/>
    <tripinfo id="flow7.2" depart="71.70" departLane="E1_0" departPos="5.10" departPosLat="0.00" departSpeed="0.00" departDelay="0.00" arrival="368.10" arrivalLane="-E4_2" arrivalPos="86.40" arrivalPosLat="0.00" arrivalSpeed="12.89" duration="296.40" routeLength="274.04" waitingTime="224.80" waitingCount="3" stopTime="0.00" timeLoss="275.37" rerouteNo="0" devices="tripinfo_flow7.2" vType="type1" speedFactor="1.01" vaporized=""/>
    <tripinfo id="flow18.4" depart="139.60" departLane="-E6_0" departPos="5.10" departPosLat="0.00" departSpeed="0.00" departDelay="0.00" arrival="369.30" arrivalLane="-E1_2" arrivalPos="86.40" arrivalPosLat="0.00" arrivalSpeed="13.46" duration="229.70" routeLength="289.52" waitingTime="166.10" waitingCount="3" stopTime="0.00" timeLoss="208.06" rerouteNo="0" devices="tripinfo_flow18.4" vType="type1" speedFactor="1.10" vaporized=""/>
    <tripinfo id="flow2.2" depart="125.40" departLane="E2_0" departPos="5.10" departPosLat="0.00" departSpeed="0.00" departDelay="0.00" arrival="369.40" arrivalLane="-E4_2" arrivalPos="86.40" arrivalPosLat="0.00" arrivalSpeed="13.24" duration="244.00" routeLength="292.21" waitingTime="180.40" waitingCount="24" stopTime="0.00" timeLoss="222.39" rerouteNo="0" devices="tripinfo_flow2.2" vType="type1" speedFactor="1.02" vaporized=""/>
    <tripinfo id="flow26.3" depart="346.10" departLane="E4_0" departPos="5.10" departPosLat="0.00" departSpeed="0.00" departDelay="3.80" arrival="371.70" arrivalLane="E6_1" arrivalPos="86.40" arrivalPosLat="0.00" arrivalSpeed="11.57" duration="25.60" routeLength="194.90" waitingTime="0.00" waitingCount="0" stopTime="0.00" timeLoss="8.73" rerouteNo="0" devices="tripinfo_flow26.3" vType="type1" speedFactor="0.83" vaporized=""/>
    <tripinfo id="flow16.0" depart="310.50" departLane="-E6_0" departPos="5.10" departPosLat="0.00" departSpeed="0.00" departDelay="0.00" arrival="375.90" arrivalLane="E5_0" arrivalPos="86.40" arrivalPosLat="0.00" arrivalSpeed="11.97" duration="65.40" routeLength="176.73" waitingTime="33.40" waitingCount="1" stopTime="0.00" timeLoss="51.90" rerouteNo="0" devices="tripinfo_flow16.0" vType="type1" speedFactor="1.00" vaporized=""/>
    <tripinfo id="flow10.3" depart="318.60" departLane="-E0_0" departPos="5.10" departPosLat="0.00" departSpeed="0.00" departDelay="0.00" arrival="376.00" arrivalLane="-E2_0" arrivalPos="86.40" arrivalPosLat="0.00" arrivalSpeed="11.98" duration="57.40" routeLength="176.73" waitingTime="25.10" waitingCount="1" stopTime="0.00" timeLoss="44.04" rerouteNo="0" devices="tripinfo_flow10.3" vType="type1" speedFactor="1.15" vaporized=""/>
    <tripinfo id="flow11.3" depart="333.70" departLane="-E0_0" departPos="5.10" departPosLat="0.00" departSpeed="0.00" departDelay="0.00" arrival="377.20" arrivalLane="-E1_1" arrivalPos="86.40" arrivalPosLat="0.00" arrivalSpeed="13.20" duration="43.50" routeLength="194.90" waitingTime="9.90" waitingCount="1" stopTime="0.00" timeLoss="29.38" rerouteNo="0" devices="tripinfo_flow11.3" vType="type1" speedFactor="1.01" vaporized=""/>
    <tripinfo id="flow5.1" depart="341.40" departLane="E1_0" departPos="5.10" departPosLat="0.00" departSpeed="0.00" departDelay="0.00" arrival="377.20" arrivalLane="E0_1" arrivalPos="86.40" arrivalPosLat="0.00" arrivalSpeed="12.36" duration="35.80" routeLength="194.90" waitingTime="2.40" waitingCount="1" stopTime="0.00" timeLoss="19.98" rerouteNo="0" devices="tripinfo_flow5.1" vType="type1" speedFactor="0.89" vaporized=""/>
    <tripinfo id="flow25.1" depart="295.40" departLane="E4_0" departPos="5.10" departPosLat="0.00" departSpeed="0.00" departDelay="0.00" arrival="412.80" arrivalLane="E5_2" arrivalPos="86.40" arrivalPosLat="0.00" arrivalSpeed="12.93" duration="117.40" routeLength="192.21" waitingTime="82.30" waitingCount="1" stopTime="0.00" timeLoss="102.66" rerouteNo="0" devices="tripinfo_flow25.1" vType="type1" speedFactor="0.98" vaporized=""/>
    <tripinfo id="flow22.5" depart="328.10" departLane="-E5_0" departPos="5.10" departPosLat="0.00" departSpeed="0.00" departDelay="0.00" arrival="420.70" arrivalLane="E0_0" arrivalPos="86.40" arrivalPosLat="0.00" arrivalSpeed="11.82" duration="92.60" routeLength="276.73" waitingTime="52.10" waitingCount="1" stopTime="0.00" timeLoss="71.93" rerouteNo="0" devices="tripinfo_flow22.5" vType="type1" speedFactor="1.00" vaporized=""/>
    <tripinfo id="flow27.1" depart="318.30" departLane="E4_0" departPos="5.10" departPosLat="0.00" departSpeed="0.00" departDelay="0.00" arrival="422.00" arrivalLane="E0_0" arrivalPos="86.40" arrivalPosLat="0.00" arrivalSpeed="12.45" duration="103.70" routeLength="258.56" waitingTime="49.60" waitingCount="2" stopTime="0.00" timeLoss="82.95" rerouteNo="0" devices="tripinfo_flow27.1" vType="type1" speedFactor="0.97" vaporized=""/>
    <tripinfo id="flow8.2" depart="310.10" departLane="E1_0" departPos="5.10" departPosLat="0.00" departSpeed="0.00" departDelay="0.00" arrival="422.20" arrivalLane="E5_0" arrivalPos="86.40" arrivalPosLat="0.00" arrivalSpeed="13.17" duration="112.10" routeLength="276.73" waitingTime="62.20" waitingCount="2" stopTime="0.00" timeLoss="91.48" rerouteNo="0" devices="tripinfo_flow8.2" vType="type1" speedFactor="1.03" vaporized=""/>
    <tripinfo id="flow27.2" depart="341.70" departLane="E4_0" departPos="5.10" departPosLat="0.00" departSpeed="0.00" departDelay="1.50" arrival="423.30" arrivalLane="E0_0" arrivalPos="86.40" arrivalPosLat="0.00" arrivalSpeed="12.84" duration="81.60" routeLength="258.56" waitingTime="21.10" waitingCount="1" stopTime="0.00" timeLoss="61.53" rerouteNo="0" devices="tripinfo_flow27.2" vType="type1" speedFactor="1.02" vaporized=""/>
    <tripinfo id="flow8.3" depart="347.30" departLane="E1_0" departPos="5.10" departPosLat="0.00" departSpeed="0.00" departDelay="0.00" arrival="423.60" arrivalLane="E5_0" arrivalPos="86.40" arrivalPosLat="0.00" arrivalSpeed="12.79" duration="76.30" routeLength="276.73" waitingTime="27.60" waitingCount="1" stopTime="0.00" timeLoss="53.78" rerouteNo="0" devices="tripinfo_flow8.3" vType="type1" speedFactor="0.92" vaporized=""/>
    <tripinfo id="flow14.1" depart="360.90" departLane="-E0_0" departPos="5.10" departPosLat="0.00" departSpeed="0.00" departDelay="0.00" arrival="424.50" arrivalLane="E6_0" arrivalPos="86.40" arrivalPosLat="-0.00" arrivalSpeed="13.19" duration="63.60" routeLength="274.04" waitingTime="19.00" waitingCount="1" stopTime="0.00" timeLoss="42.73" rerouteNo="0" devices="tripinfo_flow14.1" vType="type1" speedFactor="1.06" vaporized=""/>
    <tripinfo id="flow14.2" depart="383.40" departLane="-E0_0" departPos="5.10" departPosLat="0.00" departSpeed="0.00" departDelay="0.00" arrival="428.60" arrivalLane="E6_0" arrivalPos="86.40" arrivalPosLat="-0.00" arrivalSpeed="12.93" duration="45.20" routeLength="274.04" waitingTime="0.00" waitingCount="0" stopTime="0.00" timeLoss="23.40" rerouteNo="0" devices="tripinfo_flow14.2" vType="type1" speedFactor="0.97" vaporized=""/>
    <tripinfo id="flow21.4" depart="405.60" departLane="-E5_0" departPos="5.10" departPosLat="0.00" departSpeed="0.00" departDelay="0.00" arrival="431.60" arrivalLane="-E4_0" arrivalPos="86.40" arrivalPosLat="0.00" arrivalSpeed="12.87" duration="26.00" routeLength="176.73" waitingTime="0.00" waitingCount="0" stopTime="0.00" timeLoss="11.48" rerouteNo="0" devices="tripinfo_flow21.4" vType="type1" speedFactor="0.93" vaporized=""/>
    <tripinfo id="flow2.3" depart="151.90" departLane="E2_0" departPos="5.10" departPosLat="0.00" departSpeed="0.00" departDelay="0.00" arrival="457.90" arrivalLane="-E4_2" arrivalPos="86.40" arrivalPosLat="0.00" arrivalSpeed="12.93" duration="306.00" routeLength="292.21" waitingTime="244.20" waitingCount="4" stopTime="0.00" timeLoss="283.35" rerouteNo="0" devices="tripinfo_flow2.3" vType="type1" speedFactor="0.96" vaporized=""/>
    <tripinfo id="flow1.1" depart="391.00" departLane="E2_0" departPos="5.10" departPosLat="0.00" departSpeed="0.00" departDelay="0.00" arrival="457.90" arrivalLane="E0_2" arrivalPos="86.40" arrivalPosLat="0.00" arrivalSpeed="12.96" duration="66.90" routeLength="192.21" waitingTime="33.90" waitingCount="1" stopTime="0.00" timeLoss="52.44" rerouteNo="0" devices="tripinfo_flow1.1" vType="type1" speedFactor="1.01" vaporized=""/>
    <tripinfo id="flow23.2" depart="172.30" departLane="-E5_0" departPos="5.10" departPosLat="0.00" departSpeed="0.00" departDelay="0.00" arrival="458.10" arrivalLane="-E1_2" arrivalPos="86.40" arrivalPosLat="0.00" arrivalSpeed="12.97" duration="285.80" routeLength="292.21" waitingTime="216.40" waitingCount="5" stopTime="0.00" timeLoss="264.33" rerouteNo="0" devices="tripinfo_flow23.2" vType="type1" speedFactor="1.09" vaporized=""/>
    <tripinfo id="flow20.1" depart="358.10" departLane="-E5_0" departPos="5.10" departPosLat="0.00" departSpeed="0.00" departDelay="0.00" arrival="458.10" arrivalLane="E6_2" arrivalPos="86.40" arrivalPosLat="0.00" arrivalSpeed="12.96" duration="100.00" routeLength="192.21" waitingTime="66.50" waitingCount="1" stopTime="0.00" timeLoss="85.73" rerouteNo="0" devices="tripinfo_flow20.1" vType="type1" speedFactor="1.09" vaporized=""/>
    <tripinfo id="flow18.5" depart="178.80" departLane="-E6_0" departPos="5.10" departPosLat="0.00" departSpeed="0.00" departDelay="0.00" arrival="459.50" arrivalLane="-E1_2" arrivalPos="86.40" arrivalPosLat="0.00" arrivalSpeed="12.15" duration="280.70" routeLength="289.52" waitingTime="204.20" waitingCount="4" stopTime="0.00" timeLoss="255.52" rerouteNo="0" devices="tripinfo_flow18.5" vType="type1" speedFactor="0.88" vaporized=""/>
    <tripinfo id="flow20.2" depart="374.60" departLane="-E5_0" departPos="5.10" departPosLat="0.00" departSpeed="0.00" departDelay="3.00" arrival="459.50" arrivalLane="E6_2" arrivalPos="86.40" arrivalPosLat="0.00" arrivalSpeed="12.58" duration="84.90" routeLength="192.21" waitingTime="45.00" waitingCount="1" stopTime="0.00" timeLoss="68.90" rerouteNo="0" devices="tripinfo_flow20.2" vType="type1" speedFactor="0.91" vaporized=""/>
    <tripinfo id="flow7.3" depart="262.00" departLane="E1_0" departPos="5.10" departPosLat="0.00" departSpeed="0.00" departDelay="0.00" arrival="460.00" arrivalLane="-E4_2" arrivalPos="86.40" arrivalPosLat="0.00" arrivalSpeed="13.37" duration="198.00" routeLength="274.04" waitingTime="140.30" waitingCount="4" stopTime="0.00" timeLoss="176.97" rerouteNo="0" devices="tripinfo_flow7.3" vType="type1" speedFactor="1.02" vaporized=""/>
    <tripinfo id="flow16.1" depart="413.80" departLane="-E6_0" departPos="5.10" departPosLat="0.00" departSpeed="0.00" departDelay="0.00" arrival="465.50" arrivalLane="E5_0" arrivalPos="86.40" arrivalPosLat="0.00" arrivalSpeed="12.01" duration="51.70" routeLength="176.73" waitingTime="20.00" waitingCount="1" stopTime="0.00" timeLoss="36.16" rerouteNo="0" devices="tripinfo_flow16.1" vType="type1" speedFactor="0.87" vaporized=""/>
    <tripinfo id="flow26.4" depart="384.60" departLane="E4_0" departPos="5.10" departPosLat="0.00" departSpeed="0.00" departDelay="0.00" arrival="467.20" arrivalLane="E6_0" arrivalPos="86.40" arrivalPosLat="0.00" arrivalSpeed="13.10" duration="82.60" routeLength="194.90" waitingTime="49.30" waitingCount="1" stopTime="0.00" timeLoss="67.84" rerouteNo="0" devices="tripinfo_flow26.4" vType="type1" speedFactor="0.95" vaporized=""/>
    <tripinfo id="flow26.5" depart="416.90" departLane="E4_0" departPos="5.10" departPosLat="0.00" departSpeed="0.00" departDelay="0.00" arrival="467.20" arrivalLane="E6_1" arrivalPos="86.40" arrivalPosLat="0.00" arrivalSpeed="13.09" duration="50.30" routeLength="194.90" waitingTime="16.80" waitingCount="1" stopTime="0.00" timeLoss="36.27" rerouteNo="0" devices="tripinfo_flow26.5" vType="type1" speedFactor="1.01" vaporized=""/>
    <tripinfo id="flow11.4" depart="386.50" departLane="-E0_0" departPos="5.10" departPosLat="0.00" departSpeed="0.00" departDelay="0.20" arrival="467.30" arrivalLane="-E1_0" arrivalPos="86.40" arrivalPosLat="-0.00" arrivalSpeed="12.39" duration="80.80" routeLength="194.90" waitingTime="47.10" waitingCount="1" stopTime="0.00" timeLoss="65.05" rerouteNo="0" devices="tripinfo_flow11.4" vType="type1" speedFactor="0.89" vaporized=""/>
